gitwip/__init__.py
gitwip/main.py
gitwip-0.1.0.dist-info/METADATA
gitwip-0.1.0.dist-info/WHEEL
gitwip-0.1.0.dist-info/entry_points.txt
gitwip-0.1.0.dist-info/licenses/LICENSE
gitwip-0.1.0.dist-info/RECORD
