Metadata-Version: 2.4
Name: gitwip
Version: 0.1.0
Summary: Lists non-primary git branches in a directory tree.
Project-URL: Homepage, https://github.com/4mbl/gitwip
Project-URL: Bug Tracker, https://github.com/4mbl/gitwip/issues
Project-URL: Changelog, https://github.com/4mbl/gitwip/blob/main/CHANGELOG.md
Project-URL: Documentation, https://github.com/4mbl/gitwip/blob/main/README.md
Project-URL: Repository, https://github.com/4mbl/gitwip
Author: 4MBL
License: MIT License
License-File: LICENSE
Classifier: Development Status :: 5 - Production/Stable
Classifier: Environment :: Console
Classifier: Intended Audience :: Developers
Classifier: License :: OSI Approved :: MIT License
Classifier: Natural Language :: English
Classifier: Operating System :: OS Independent
Classifier: Programming Language :: Python :: 3
Classifier: Programming Language :: Python :: 3.9
Classifier: Programming Language :: Python :: 3.10
Classifier: Programming Language :: Python :: 3.11
Classifier: Programming Language :: Python :: 3.12
Classifier: Programming Language :: Python :: 3.13
Classifier: Programming Language :: Python :: Implementation :: CPython
Classifier: Topic :: Software Development
Classifier: Topic :: Utilities
Classifier: Typing :: Typed
Requires-Python: >=3.10
Requires-Dist: fortext<1.2.0,>=1.1.2
